huaweicloudsdkmpc/__init__.py
huaweicloudsdkmpc/v1/__init__.py
huaweicloudsdkmpc/v1/mpc_async_client.py
huaweicloudsdkmpc/v1/mpc_client.py
huaweicloudsdkmpc/v1/model/__init__.py
huaweicloudsdkmpc/v1/model/additional_manifests.py
huaweicloudsdkmpc/v1/model/agencies_task_req.py
huaweicloudsdkmpc/v1/model/animated_graphics_output_param.py
huaweicloudsdkmpc/v1/model/animated_graphics_task.py
huaweicloudsdkmpc/v1/model/audio.py
huaweicloudsdkmpc/v1/model/audio_file.py
huaweicloudsdkmpc/v1/model/audio_info.py
huaweicloudsdkmpc/v1/model/audio_process.py
huaweicloudsdkmpc/v1/model/audio_track.py
huaweicloudsdkmpc/v1/model/av_parameters.py
huaweicloudsdkmpc/v1/model/basic_task_info.py
huaweicloudsdkmpc/v1/model/basic_watermark.py
huaweicloudsdkmpc/v1/model/bucket_authorized_req.py
huaweicloudsdkmpc/v1/model/cancel_remux_task_request.py
huaweicloudsdkmpc/v1/model/cancel_remux_task_response.py
huaweicloudsdkmpc/v1/model/clip_info.py
huaweicloudsdkmpc/v1/model/common.py
huaweicloudsdkmpc/v1/model/common_create_task_req.py
huaweicloudsdkmpc/v1/model/common_create_task_rsp.py
huaweicloudsdkmpc/v1/model/common_query_task_rsp.py
huaweicloudsdkmpc/v1/model/common_task.py
huaweicloudsdkmpc/v1/model/common_task_meta.py
huaweicloudsdkmpc/v1/model/concat_info.py
huaweicloudsdkmpc/v1/model/create_agencies_task_request.py
huaweicloudsdkmpc/v1/model/create_agencies_task_response.py
huaweicloudsdkmpc/v1/model/create_animated_graphics_task_req.py
huaweicloudsdkmpc/v1/model/create_animated_graphics_task_request.py
huaweicloudsdkmpc/v1/model/create_animated_graphics_task_response.py
huaweicloudsdkmpc/v1/model/create_editing_job_req.py
huaweicloudsdkmpc/v1/model/create_editing_job_request.py
huaweicloudsdkmpc/v1/model/create_editing_job_response.py
huaweicloudsdkmpc/v1/model/create_extract_task_req.py
huaweicloudsdkmpc/v1/model/create_extract_task_request.py
huaweicloudsdkmpc/v1/model/create_extract_task_response.py
huaweicloudsdkmpc/v1/model/create_mb_tasks_report_request.py
huaweicloudsdkmpc-3.1.184.dist-info/METADATA
huaweicloudsdkmpc-3.1.184.dist-info/WHEEL
huaweicloudsdkmpc-3.1.184.dist-info/licenses/LICENSE
huaweicloudsdkmpc-3.1.184.dist-info/RECORD
